ukro_g2p/__init__.py
ukro_g2p/predict.py
ukro_g2p/test.py
ukro_g2p/tokenization.py
ukro_g2p/train.py
ukro_g2p/trainer.py
ukro_g2p/configs/ukro_base_uncased.config
ukro_g2p/datasets/__init__.py
ukro_g2p/datasets/lexicon_datasets.py
ukro_g2p/models/__init__.py
ukro_g2p/models/g2p_model.py
ukro_g2p/models/modules.py
ukro_g2p/utils/__init__.py
ukro_g2p/utils/infolog.py
ukro_g2p/utils/lexicon_util.py
ukro_g2p/utils/util.py
ukro_g2p-0.1.5.dist-info/METADATA
ukro_g2p-0.1.5.dist-info/WHEEL
ukro_g2p-0.1.5.dist-info/top_level.txt
ukro_g2p-0.1.5.dist-info/RECORD
