Metadata-Version: 2.1
Name: ukro-g2p
Version: 0.1.5
Summary: NN based grapheme to phoneme model for Ukrainian language
Home-page: https://github.com/kosti4ka/ukro_g2p
Author: Kostiantyn Pylypenko
Author-email: k.pylypenko@hotmail.com
License: MIT
Keywords: Ukrainian grapheme to phoneme
Platform: UNKNOWN
Classifier: License :: OSI Approved :: MIT License
Classifier: Intended Audience :: Developers
Classifier: Intended Audience :: Science/Research
Classifier: Operating System :: OS Independent
Classifier: Programming Language :: Python
Classifier: Programming Language :: Python :: 3
Classifier: Topic :: Software Development :: Libraries
Classifier: Topic :: Software Development :: Libraries :: Python Modules
